{
  "user": {
    "nrp": "5446944",
    "name": "hahahshs",
    "unit": "renmin"
  },
  "location": {
    "latitude": -5.3595699,
    "longitude": 105.3072636,
    "accuracy": 100,
    "timestamp": 1750643955463
  },
  "timestamp": "2025-06-23T01:59:24.043Z",
  "security": {
    "ip": "36.68.131.44",
    "fingerprint": "bae0c5af98977ebc9051b73eb72476d9",
    "submittedAt": "2025-06-23T01:59:28.582Z"
  },
  "files": {
    "dataFile": "attendance/2025-06-23/data/2025-06-23T01-59-24-043Z_5446944.json",
    "photoFile": "attendance/2025-06-23/photos/2025-06-23T01-59-24-043Z_5446944.jpeg"
  }
}